isc_dhcp_leases/__init__.py
isc_dhcp_leases/iscdhcpleases.py
isc_dhcp_leases/test_iscDhcpLeases.py
isc_dhcp_leases/test_lease.py
isc_dhcp_leases/test_lease6.py
isc_dhcp_leases-0.10.0.dist-info/LICENSE
isc_dhcp_leases-0.10.0.dist-info/METADATA
isc_dhcp_leases-0.10.0.dist-info/WHEEL
isc_dhcp_leases-0.10.0.dist-info/top_level.txt
isc_dhcp_leases-0.10.0.dist-info/RECORD
